liveatlas/DateAndTime.py
liveatlas/Player.py
liveatlas/Server.py
liveatlas/Town.py
liveatlas/__init__.py
liveatlas/main.py
liveatlas-0.0.6.dist-info/METADATA
liveatlas-0.0.6.dist-info/WHEEL
liveatlas-0.0.6.dist-info/top_level.txt
liveatlas-0.0.6.dist-info/RECORD
