Metadata-Version: 2.1
Name: liveatlas
Version: 0.0.6
Summary: liveatlas-API
Home-page: UNKNOWN
Author: Sam
Author-email: UNKNOWN
License: UNKNOWN
Keywords: python,first package
Platform: UNKNOWN
Classifier: Programming Language :: Python :: 3
Classifier: Operating System :: MacOS :: MacOS X
Classifier: Operating System :: Microsoft :: Windows
Requires-Dist: datetime
Requires-Dist: requests
Requires-Dist: re
